libpbskids_dl/__init__.py
libpbskids_dl/api.py
libpbskids_dl-3.2.1.dist-info/METADATA
libpbskids_dl-3.2.1.dist-info/WHEEL
libpbskids_dl-3.2.1.dist-info/licenses/LICENSE
libpbskids_dl-3.2.1.dist-info/RECORD
